rainbow/__init__.py
rainbow/cobot.py
rb_api_python-0.0.5.dist-info/METADATA
rb_api_python-0.0.5.dist-info/WHEEL
rb_api_python-0.0.5.dist-info/top_level.txt
rb_api_python-0.0.5.dist-info/RECORD
