Metadata-Version: 2.1
Name: rb-api-python
Version: 0.0.5
Summary: Python wrapper for rarinbow robotics cobot
Home-page: https://github.com/messy-snail/rb-api/
Author: Hansol Kang, Hyojoon Lee
Author-email: hskang@rainbow-robotics.com, hyojoon_lee04@rainbow-robotics.com
License: UNKNOWN
Platform: UNKNOWN
Classifier: Programming Language :: Python :: 3
Classifier: License :: OSI Approved :: MIT License
Classifier: Operating System :: OS Independent
Requires-Python: >=3.7
